jaxflow/__init__.py
jaxflow-0.1.1.dist-info/METADATA
jaxflow-0.1.1.dist-info/WHEEL
jaxflow-0.1.1.dist-info/top_level.txt
jaxflow-0.1.1.dist-info/RECORD
