Metadata-Version: 2.4
Name: jaxflow
Version: 0.1.1
Summary: A lightweight neural-network library built on JAX
Home-page: https://github.com/mthd98/JAXFlow
Author: muntadher hussein
Author-email: mentzerhussein@gmail.com
License: Apache-2.0
Classifier: Programming Language :: Python :: 3
Classifier: Programming Language :: Python :: 3.8
Classifier: License :: OSI Approved :: Apache Software License
Classifier: Operating System :: OS Independent
Requires-Python: >=3.8
Requires-Dist: jax>=0.4.0
Requires-Dist: numpy>=2.2.0
Requires-Dist: optax>=0.2.0
